py27hash/__init__.py
py27hash/dict.py
py27hash/hash.py
py27hash/key.py
py27hash/set.py
py27hash-1.1.0.dist-info/LICENSE
py27hash-1.1.0.dist-info/METADATA
py27hash-1.1.0.dist-info/WHEEL
py27hash-1.1.0.dist-info/top_level.txt
py27hash-1.1.0.dist-info/RECORD
