Metadata-Version: 2.1
Name: py27hash
Version: 1.1.0
Summary: Python 2.7 hashing and iteration in Python 3+
Home-page: https://github.com/neuml/py27hash
Author: NeuML
License: MIT License: http://opensource.org/licenses/MIT
Download-URL: https://pypi.org/project/py27hash/
Project-URL: Documentation, https://github.com/neuml/py27hash
Project-URL: Issue Tracker, https://github.com/neuml/py27hash/issues
Project-URL: Source Code, https://github.com/neuml/py27hash
Keywords: python hash iteration migration
Platform: UNKNOWN
Classifier: License :: OSI Approved :: MIT License
Classifier: Operating System :: OS Independent
Classifier: Programming Language :: Python :: 2
Classifier: Programming Language :: Python :: 3
Classifier: Topic :: Software Development :: Libraries
Requires-Python: >=2.7
